ZhuiqiuDaimaZhiliang/README.md
ZhuiqiuDaimaZhiliang/__init__.py
ZhuiqiuDaimaZhiliang/__main__.py
ZhuiqiuDaimaZhiliang/file.epub
ZhuiqiuDaimaZhiliang/index.html
ZhuiqiuDaimaZhiliang/css/__init__.py
ZhuiqiuDaimaZhiliang/css/annotations.css
ZhuiqiuDaimaZhiliang/css/main.css
ZhuiqiuDaimaZhiliang/css/normalize.css
ZhuiqiuDaimaZhiliang/css/popup.css
ZhuiqiuDaimaZhiliang/font/__init__.py
ZhuiqiuDaimaZhiliang/font/fontello.eot
ZhuiqiuDaimaZhiliang/font/fontello.svg
ZhuiqiuDaimaZhiliang/font/fontello.ttf
ZhuiqiuDaimaZhiliang/font/fontello.woff
ZhuiqiuDaimaZhiliang/img/__init__.py
ZhuiqiuDaimaZhiliang/img/annotator-glyph-sprite.png
ZhuiqiuDaimaZhiliang/img/annotator-icon-sprite.png
ZhuiqiuDaimaZhiliang/img/apple-touch-icon.png
ZhuiqiuDaimaZhiliang/img/cancelfullscreen.png
ZhuiqiuDaimaZhiliang/img/close.png
ZhuiqiuDaimaZhiliang/img/fullscreen.png
ZhuiqiuDaimaZhiliang/img/loader.gif
ZhuiqiuDaimaZhiliang/img/menu-icon.png
ZhuiqiuDaimaZhiliang/img/save.png
ZhuiqiuDaimaZhiliang/img/saved.png
ZhuiqiuDaimaZhiliang/img/settings-s.png
ZhuiqiuDaimaZhiliang/img/settings.png
ZhuiqiuDaimaZhiliang/img/star.png
ZhuiqiuDaimaZhiliang/js/__init__.py
ZhuiqiuDaimaZhiliang/js/epub.js
ZhuiqiuDaimaZhiliang/js/epub.min.js
ZhuiqiuDaimaZhiliang/js/epub.min.map
ZhuiqiuDaimaZhiliang/js/hooks.min.js
ZhuiqiuDaimaZhiliang/js/hooks.min.map
ZhuiqiuDaimaZhiliang/js/reader.js
ZhuiqiuDaimaZhiliang/js/reader.js.map
ZhuiqiuDaimaZhiliang/js/reader.min.js
ZhuiqiuDaimaZhiliang/js/reader.min.map
ZhuiqiuDaimaZhiliang/js/hooks/__init__.py
ZhuiqiuDaimaZhiliang/js/hooks/extensions/__init__.py
ZhuiqiuDaimaZhiliang/js/hooks/extensions/highlight.js
ZhuiqiuDaimaZhiliang/js/libs/__init__.py
ZhuiqiuDaimaZhiliang/js/libs/jquery.min.js
ZhuiqiuDaimaZhiliang/js/libs/localforage.min.js
ZhuiqiuDaimaZhiliang/js/libs/screenfull.js
ZhuiqiuDaimaZhiliang/js/libs/screenfull.min.js
ZhuiqiuDaimaZhiliang/js/libs/zip.min.js
ZhuiqiuDaimaZhiliang/js/plugins/__init__.py
ZhuiqiuDaimaZhiliang/js/plugins/hypothesis.js
zhuiqiu_daima_zhiliang-2024.3.2.0.dist-info/METADATA
zhuiqiu_daima_zhiliang-2024.3.2.0.dist-info/WHEEL
zhuiqiu_daima_zhiliang-2024.3.2.0.dist-info/entry_points.txt
zhuiqiu_daima_zhiliang-2024.3.2.0.dist-info/top_level.txt
zhuiqiu_daima_zhiliang-2024.3.2.0.dist-info/RECORD
